barebonesnn/__init__.py
barebonesnn/layer.py
barebonesnn/mlp.py
barebonesnn/neuron.py
barebonesnn/value.py
test/__init__.py
test/test_layer.py
test/test_mlp.py
test/test_neuron.py
test/test_value.py
barebonesnn-0.1.1.dist-info/LICENSE
barebonesnn-0.1.1.dist-info/METADATA
barebonesnn-0.1.1.dist-info/WHEEL
barebonesnn-0.1.1.dist-info/top_level.txt
barebonesnn-0.1.1.dist-info/RECORD
