Metadata-Version: 2.1
Name: barebonesnn
Version: 0.1.1
Summary: A neural network library built from scratch.
Home-page: https://github.com/AmirMohammadiKarbalaei/BareBonesNN/barebonesnn
Author: Amir Mohammadikarbalaei
Author-email: a.mohammadikarbalaei@gmail.com
Requires-Python: >=3.6
License-File: LICENSE
Requires-Dist: numpy >=1.21.0
